gsdggs/__init__.py
gsdggs/sf_functions.py
geosparql_dggs-0.2.dist-info/LICENSE
geosparql_dggs-0.2.dist-info/METADATA
geosparql_dggs-0.2.dist-info/WHEEL
geosparql_dggs-0.2.dist-info/top_level.txt
geosparql_dggs-0.2.dist-info/RECORD
