Metadata-Version: 2.1
Name: geosparql-dggs
Version: 0.2
Summary: GeoSPARQL DGGS functions implemented as SPARQL extension in RDFLib
Home-page: https://github.com/rdflib/geosparql-dggs
Maintainer: David Habgood
Maintainer-email: david.habgood@surroundaustralia.com
License: BSD
Platform: any
Classifier: Programming Language :: Python
Classifier: Programming Language :: Python :: 3
Classifier: Programming Language :: Python :: 3.8
Classifier: License :: OSI Approved :: BSD License
Classifier: Topic :: Software Development :: Libraries :: Python Modules
Classifier: Operating System :: OS Independent
Classifier: Natural Language :: English
License-File: LICENSE
Requires-Dist: rdflib (>=6.0.0)
Requires-Dist: rhealpix-sf
